{
  "version": "1.0.0",
  "restore": {
    "projectUniqueName": "C:\\Projects Repositories\\C#\\ConsoleApp\\ConsoleApp.csproj",
    "projectName": "ConsoleApp",
    "projectPath": "C:\\Projects Repositories\\C#\\ConsoleApp\\ConsoleApp.csproj",
    "outputPath": "C:\\Projects Repositories\\C#\\ConsoleApp\\obj\\",
    "projectStyle": "PackageReference",
    "fallbackFolders": [
      "C:\\Program Files\\dotnet\\sdk\\NuGetFallbackFolder"
    ],
    "originalTargetFrameworks": [
      "netcoreapp2.1"
    ],
    "frameworks": {
      "netcoreapp2.1": {
        "projectReferences": {
          "C:\\Projects Repositories\\C#\\BLL\\BLL.csproj": {
            "projectPath": "C:\\Projects Repositories\\C#\\BLL\\BLL.csproj"
          },
          "C:\\Projects Repositories\\C#\\Domain\\Domain.csproj": {
            "projectPath": "C:\\Projects Repositories\\C#\\Domain\\Domain.csproj"
          },
          "C:\\Projects Repositories\\C#\\Initializers\\Initializers.csproj": {
            "projectPath": "C:\\Projects Repositories\\C#\\Initializers\\Initializers.csproj"
          },
          "C:\\Projects Repositories\\C#\\MenuSystem\\MenuSystem.csproj": {
            "projectPath": "C:\\Projects Repositories\\C#\\MenuSystem\\MenuSystem.csproj"
          },
          "C:\\Projects Repositories\\C#\\UI\\UI.csproj": {
            "projectPath": "C:\\Projects Repositories\\C#\\UI\\UI.csproj"
          }
        }
      }
    },
    "warningProperties": {
      "warnAsError": [
        "NU1605"
      ]
    }
  },
  "frameworks": {
    "netcoreapp2.1": {
      "dependencies": {
        "Microsoft.EntityFrameworkCore.Design": {
          "target": "Package",
          "version": "[2.2.0, )"
        },
        "Microsoft.EntityFrameworkCore.Tools.DotNet": {
          "target": "Package",
          "version": "[2.0.3, )"
        },
        "Microsoft.NETCore.App": {
          "suppressParent": "All",
          "target": "Package",
          "version": "[2.1.0, )",
          "autoReferenced": true
        }
      },
      "imports": [
        "net461"
      ],
      "assetTargetFallback": true,
      "warn": true
    }
  }
}